drf_rw_serializers/__init__.py
drf_rw_serializers/apps.py
drf_rw_serializers/generics.py
drf_rw_serializers/mixins.py
drf_rw_serializers/viewsets.py
drf_rw_serializers-1.4.0.dist-info/AUTHORS.rst
drf_rw_serializers-1.4.0.dist-info/LICENSE.txt
drf_rw_serializers-1.4.0.dist-info/METADATA
drf_rw_serializers-1.4.0.dist-info/WHEEL
drf_rw_serializers-1.4.0.dist-info/RECORD
