Metadata-Version: 2.1
Name: drf-rw-serializers
Version: 1.4.0
Summary: Generic views, viewsets and mixins that extend the Django REST Framework ones adding separated serializers for read and write operations
License: MIT
Author: Vinta Software
Author-email: contact@vinta.com.br
Requires-Python: >=3.8,<4.0
Classifier: License :: OSI Approved :: MIT License
Classifier: Programming Language :: Python :: 3
Classifier: Programming Language :: Python :: 3.8
Classifier: Programming Language :: Python :: 3.9
Classifier: Programming Language :: Python :: 3.10
Classifier: Programming Language :: Python :: 3.11
Classifier: Programming Language :: Python :: 3.12
Requires-Dist: djangorestframework (>=3.14.0,<4.0.0)
Project-URL: Bug Tracker, https://github.com/vintasoftware/drf-rw-serializers/issues
Project-URL: Changelog, https://github.com/vintasoftware/drf-rw-serializers/blob/main/CHANGELOG.rst
Project-URL: Documentation, https://drf-rw-serializers.readthedocs.io
Project-URL: Homepage, https://github.com/vintasoftware/drf-rw-serializers
Project-URL: Source, https://github.com/vintasoftware/drf-rw-serializers/
